{"name":"Groklabs-website","tagline":"Github Pages website for Groklabs.com","body":"### Grok\r\n/ɡräk/\r\nverb *informal*\r\nunderstand (something) intuitively or by empathy.\r\n\"because of all the commercials, children grok things immediately\"\r\n   * empathize or communicate sympathetically; establish a rapport.\r\n\r\n### Welcome to Grok Labs.\r\nWe are an Ideation and Innovation consultancy based in San Francisco. The [Founder](https://github.com/boscomonkey/) was a 2014 [Presidential Innovation Fellow](https://presidentialinnovationfellows.gov/) at the Department of Energy's [SunShot Initiative](http://energy.gov/sunshot).","google":"","note":"Don't delete this file! It's used internally to help with page regeneration."}